LICENSE
README.md
setup.cfg
setup.py
bin/sockterm
sockterm/__init__.py
sockterm/__main__.py
sockterm/cli.py
sockterm/commands.py
sockterm/completer.py
sockterm/socketio_client.py
sockterm/state.py
sockterm/version.py
sockterm.egg-info/PKG-INFO
sockterm.egg-info/SOURCES.txt
sockterm.egg-info/dependency_links.txt
sockterm.egg-info/entry_points.txt
sockterm.egg-info/requires.txt
sockterm.egg-info/top_level.txt