Metadata-Version: 2.1
Name: sockterm
Version: 0.0.1
Summary: A simple, intuitive Socket.IO CLI.
Home-page: https://gitlab.com/bbworld1/sockterm
Author: Vincent Wang
Author-email: vwangsf@gmail.com
License: MIT
Download-URL: https://gitlab.com/bbworld1/sockterm
Keywords: socketio,cli,sockterm
Platform: UNKNOWN
Classifier: Environment :: Console
Classifier: Intended Audience :: Developers
Classifier: License :: OSI Approved :: MIT License
Classifier: Programming Language :: Python
Classifier: Programming Language :: Python :: 3
Classifier: Programming Language :: Python :: 3.5
Classifier: Programming Language :: Python :: 3.6
Classifier: Programming Language :: Python :: 3.7
Classifier: Programming Language :: Python :: 3.8
Classifier: Programming Language :: Python :: 3 :: Only
Classifier: Topic :: Software Development :: Debuggers
Classifier: Topic :: System :: Logging
Classifier: Topic :: System :: Monitoring
Classifier: Topic :: System :: Networking
License-File: LICENSE
